cplot/__about__.py
cplot/__init__.py
cplot/_colors.py
cplot/_main.py
cplot/_riemann_sphere.py
cplot/_tri.py
cplot/benchmark.py
cplot-0.9.3.dist-info/LICENSE
cplot-0.9.3.dist-info/METADATA
cplot-0.9.3.dist-info/WHEEL
cplot-0.9.3.dist-info/top_level.txt
cplot-0.9.3.dist-info/RECORD
