Metadata-Version: 2.1
Name: cplot
Version: 0.9.3
Summary: Plot complex-valued functions
Author-email: Nico Schlömer <nico.schloemer@gmail.com>
License: GNU GENERAL PUBLIC LICENSE
Project-URL: Code, https://github.com/nschloe/cplot
Project-URL: Issues, https://github.com/nschloe/cplot/issues
Project-URL: Funding, https://github.com/sponsors/nschloe
Classifier: Development Status :: 4 - Beta
Classifier: Framework :: Matplotlib
Classifier: Intended Audience :: Science/Research
Classifier: License :: OSI Approved :: GNU General Public License v3 or later (GPLv3+)
Classifier: Operating System :: OS Independent
Classifier: Programming Language :: Python
Classifier: Programming Language :: Python :: 3
Classifier: Programming Language :: Python :: 3.7
Classifier: Programming Language :: Python :: 3.8
Classifier: Programming Language :: Python :: 3.9
Classifier: Programming Language :: Python :: 3.10
Classifier: Topic :: Scientific/Engineering
Classifier: Topic :: Scientific/Engineering :: Visualization
Requires-Python: >=3.7
License-File: LICENSE
Requires-Dist: matplotlib
Requires-Dist: matplotx[all] (>=0.3.10)
Requires-Dist: npx
Requires-Dist: numpy (>=1.20.0)
Provides-Extra: all
Requires-Dist: meshzoo ; extra == 'all'
Requires-Dist: pyvista ; extra == 'all'
